ExObject/DateTime.py
ExObject/ExObject.py
ExObject/ExParsel.py
ExObject/ExRedis.py
ExObject/ExStock.py
ExObject/TimeSpan.py
ExObject/__init__.py
exobject-1.0.dist-info/METADATA
exobject-1.0.dist-info/WHEEL
exobject-1.0.dist-info/top_level.txt
exobject-1.0.dist-info/RECORD
