Metadata-Version: 2.1
Name: exobject
Version: 1.0
Summary: Extend Object Code
Home-page: 
Author: LenShang
Author-email: lenshang@qq.com
Maintainer: LenShang
Maintainer-email: lenshang@qq.com
License: BSD License
Platform: all
Requires-Dist: python-dateutil
Requires-Dist: parsel
